dict2any/__about__.py
dict2any/__init__.py
dict2any/jq_path.py
dict2any/parse.py
dict2any/py.typed
dict2any/parsers/__init__.py
dict2any/parsers/any.py
dict2any/parsers/base_types.py
dict2any/parsers/class_parser.py
dict2any/parsers/dataclass.py
dict2any/parsers/dict.py
dict2any/parsers/list.py
dict2any/parsers/parser.py
dict2any/parsers/path.py
dict2any/parsers/tuple.py
dict2any/parsers/union.py
dict2any-0.0.2.dist-info/METADATA
dict2any-0.0.2.dist-info/WHEEL
dict2any-0.0.2.dist-info/licenses/LICENSE
dict2any-0.0.2.dist-info/RECORD
