Metadata-Version: 2.1
Name: dict2any
Version: 0.0.2
Summary: dict to/from dataclasses
Project-URL: Documentation, https://github.com/intentionally-left-nil/dict2any#readme
Project-URL: Issues, https://github.com/intentionally-left-nil/dict2any/issues
Project-URL: Source, https://github.com/intentionally-left-nil/dict2any
Author-email: Anil Kulkarni <anil@terminal.space>
License-Expression: MIT
License-File: LICENSE
Classifier: Development Status :: 4 - Beta
Classifier: Programming Language :: Python
Classifier: Programming Language :: Python :: 3.12
Classifier: Programming Language :: Python :: Implementation :: CPython
Classifier: Programming Language :: Python :: Implementation :: PyPy
Requires-Python: >=3.12
